LICENSE.txt
README.md
setup.cfg
setup.py
procamora_utils/__init__.py
procamora_utils/client_ssh.py
procamora_utils/interface_sqlite.py
procamora_utils/ip.py
procamora_utils/ip_unittest.py
procamora_utils/logger.py
procamora_utils/ping.py
procamora_utils/ping_unittest.py
procamora_utils/sqlite_unittest.py
procamora_utils.egg-info/PKG-INFO
procamora_utils.egg-info/SOURCES.txt
procamora_utils.egg-info/dependency_links.txt
procamora_utils.egg-info/requires.txt
procamora_utils.egg-info/top_level.txt