Metadata-Version: 2.1
Name: procamora-utils
Version: 1.7
Summary: This repository contains a set of libraries that i use in other projects
Home-page: https://github.com/procamora/python3-utils
Author: procamora
Author-email: pablojoserocamora@gmail.com
License: gpl-3.0
Download-URL: https://github.com/procamora/python3-utils/archive/v1.7.tar.gz
Keywords: sqlite,sql,sqlite3,network,fqdn,ip,ipv4,ipv6,icmp,ping,logging,color,log,ssh,paramiko
Platform: UNKNOWN
Classifier: Development Status :: 4 - Beta
Classifier: Intended Audience :: Developers
Classifier: Topic :: Software Development :: Libraries
Classifier: Topic :: Software Development :: Libraries :: Python Modules
Classifier: Topic :: System :: Networking
Classifier: Topic :: System :: Logging
Classifier: Topic :: Database
Classifier: License :: OSI Approved :: GNU General Public License v3 or later (GPLv3+)
Classifier: Programming Language :: Python :: 3.7
Classifier: Programming Language :: Python :: 3.8
Classifier: Programming Language :: Python :: 3.9
Requires-Python: <4, >=3.7
